{
  "id": 264617214,
  "node_id": "MDEwOlJlcG9zaXRvcnkyNjQ2MTcyMTQ=",
  "name": "rita",
  "full_name": "dhowe/rita",
  "private": false,
  "owner": {
    "login": "dhowe",
    "id": 737638,
    "node_id": "MDQ6VXNlcjczNzYzOA==",
    "avatar_url": "https://avatars.githubusercontent.com/u/737638?v=4",
    "gravatar_id": "",
    "url": "https://api.github.com/users/dhowe",
    "html_url": "https://github.com/dhowe",
    "followers_url": "https://api.github.com/users/dhowe/followers",
    "following_url": "https://api.github.com/users/dhowe/following{/other_user}",
    "gists_url": "https://api.github.com/users/dhowe/gists{/gist_id}",
    "starred_url": "https://api.github.com/users/dhowe/starred{/owner}{/repo}",
    "subscriptions_url": "https://api.github.com/users/dhowe/subscriptions",
    "organizations_url": "https://api.github.com/users/dhowe/orgs",
    "repos_url": "https://api.github.com/users/dhowe/repos",
    "events_url": "https://api.github.com/users/dhowe/events{/privacy}",
    "received_events_url": "https://api.github.com/users/dhowe/received_events",
    "type": "User",
    "user_view_type": "public",
    "site_admin": false
  },
  "html_url": "https://github.com/dhowe/rita",
  "description": "Website, documentation and examples for RiTa",
  "fork": false,
  "url": "https://api.github.com/repos/dhowe/rita",
  "forks_url": "https://api.github.com/repos/dhowe/rita/forks",
  "keys_url": "https://api.github.com/repos/dhowe/rita/keys{/key_id}",
  "collaborators_url": "https://api.github.com/repos/dhowe/rita/collaborators{/collaborator}",
  "teams_url": "https://api.github.com/repos/dhowe/rita/teams",
  "hooks_url": "https://api.github.com/repos/dhowe/rita/hooks",
  "issue_events_url": "https://api.github.com/repos/dhowe/rita/issues/events{/number}",
  "events_url": "https://api.github.com/repos/dhowe/rita/events",
  "assignees_url": "https://api.github.com/repos/dhowe/rita/assignees{/user}",
  "branches_url": "https://api.github.com/repos/dhowe/rita/branches{/branch}",
  "tags_url": "https://api.github.com/repos/dhowe/rita/tags",
  "blobs_url": "https://api.github.com/repos/dhowe/rita/git/blobs{/sha}",
  "git_tags_url": "https://api.github.com/repos/dhowe/rita/git/tags{/sha}",
  "git_refs_url": "https://api.github.com/repos/dhowe/rita/git/refs{/sha}",
  "trees_url": "https://api.github.com/repos/dhowe/rita/git/trees{/sha}",
  "statuses_url": "https://api.github.com/repos/dhowe/rita/statuses/{sha}",
  "languages_url": "https://api.github.com/repos/dhowe/rita/languages",
  "stargazers_url": "https://api.github.com/repos/dhowe/rita/stargazers",
  "contributors_url": "https://api.github.com/repos/dhowe/rita/contributors",
  "subscribers_url": "https://api.github.com/repos/dhowe/rita/subscribers",
  "subscription_url": "https://api.github.com/repos/dhowe/rita/subscription",
  "commits_url": "https://api.github.com/repos/dhowe/rita/commits{/sha}",
  "git_commits_url": "https://api.github.com/repos/dhowe/rita/git/commits{/sha}",
  "comments_url": "https://api.github.com/repos/dhowe/rita/comments{/number}",
  "issue_comment_url": "https://api.github.com/repos/dhowe/rita/issues/comments{/number}",
  "contents_url": "https://api.github.com/repos/dhowe/rita/contents/{+path}",
  "compare_url": "https://api.github.com/repos/dhowe/rita/compare/{base}...{head}",
  "merges_url": "https://api.github.com/repos/dhowe/rita/merges",
  "archive_url": "https://api.github.com/repos/dhowe/rita/{archive_format}{/ref}",
  "downloads_url": "https://api.github.com/repos/dhowe/rita/downloads",
  "issues_url": "https://api.github.com/repos/dhowe/rita/issues{/number}",
  "pulls_url": "https://api.github.com/repos/dhowe/rita/pulls{/number}",
  "milestones_url": "https://api.github.com/repos/dhowe/rita/milestones{/number}",
  "notifications_url": "https://api.github.com/repos/dhowe/rita/notifications{?since,all,participating}",
  "labels_url": "https://api.github.com/repos/dhowe/rita/labels{/name}",
  "releases_url": "https://api.github.com/repos/dhowe/rita/releases{/id}",
  "deployments_url": "https://api.github.com/repos/dhowe/rita/deployments",
  "created_at": "2020-05-17T08:34:27Z",
  "updated_at": "2025-06-10T17:31:52Z",
  "pushed_at": "2025-06-10T17:31:48Z",
  "git_url": "git://github.com/dhowe/rita.git",
  "ssh_url": "git@github.com:dhowe/rita.git",
  "clone_url": "https://github.com/dhowe/rita.git",
  "svn_url": "https://github.com/dhowe/rita",
  "homepage": "https://rednoise.org/rita",
  "size": 237142,
  "stargazers_count": 72,
  "watchers_count": 72,
  "language": "JavaScript",
  "has_issues": true,
  "has_projects": true,
  "has_downloads": true,
  "has_wiki": true,
  "has_pages": false,
  "has_discussions": true,
  "forks_count": 9,
  "mirror_url": null,
  "archived": false,
  "disabled": false,
  "open_issues_count": 45,
  "license": null,
  "allow_forking": true,
  "is_template": false,
  "web_commit_signoff_required": false,
  "topics": [
    "generative-text",
    "natural-language",
    "rita",
    "text-analysis",
    "text-generation"
  ],
  "visibility": "public",
  "forks": 9,
  "open_issues": 45,
  "watchers": 72,
  "default_branch": "master",
  "permissions": {
    "admin": false,
    "maintain": false,
    "push": false,
    "triage": false,
    "pull": true
  },
  "score": 1.0
}