{
  "id": 97929948,
  "node_id": "MDEwOlJlcG9zaXRvcnk5NzkyOTk0OA==",
  "name": "node-simconnect",
  "full_name": "EvenAR/node-simconnect",
  "private": false,
  "owner": {
    "login": "EvenAR",
    "id": 5177099,
    "node_id": "MDQ6VXNlcjUxNzcwOTk=",
    "avatar_url": "https://avatars.githubusercontent.com/u/5177099?v=4",
    "gravatar_id": "",
    "url": "https://api.github.com/users/EvenAR",
    "html_url": "https://github.com/EvenAR",
    "followers_url": "https://api.github.com/users/EvenAR/followers",
    "following_url": "https://api.github.com/users/EvenAR/following{/other_user}",
    "gists_url": "https://api.github.com/users/EvenAR/gists{/gist_id}",
    "starred_url": "https://api.github.com/users/EvenAR/starred{/owner}{/repo}",
    "subscriptions_url": "https://api.github.com/users/EvenAR/subscriptions",
    "organizations_url": "https://api.github.com/users/EvenAR/orgs",
    "repos_url": "https://api.github.com/users/EvenAR/repos",
    "events_url": "https://api.github.com/users/EvenAR/events{/privacy}",
    "received_events_url": "https://api.github.com/users/EvenAR/received_events",
    "type": "User",
    "user_view_type": "public",
    "site_admin": false
  },
  "html_url": "https://github.com/EvenAR/node-simconnect",
  "description": "A cross platform SimConnect client library for Node.JS",
  "fork": false,
  "url": "https://api.github.com/repos/EvenAR/node-simconnect",
  "forks_url": "https://api.github.com/repos/EvenAR/node-simconnect/forks",
  "keys_url": "https://api.github.com/repos/EvenAR/node-simconnect/keys{/key_id}",
  "collaborators_url": "https://api.github.com/repos/EvenAR/node-simconnect/collaborators{/collaborator}",
  "teams_url": "https://api.github.com/repos/EvenAR/node-simconnect/teams",
  "hooks_url": "https://api.github.com/repos/EvenAR/node-simconnect/hooks",
  "issue_events_url": "https://api.github.com/repos/EvenAR/node-simconnect/issues/events{/number}",
  "events_url": "https://api.github.com/repos/EvenAR/node-simconnect/events",
  "assignees_url": "https://api.github.com/repos/EvenAR/node-simconnect/assignees{/user}",
  "branches_url": "https://api.github.com/repos/EvenAR/node-simconnect/branches{/branch}",
  "tags_url": "https://api.github.com/repos/EvenAR/node-simconnect/tags",
  "blobs_url": "https://api.github.com/repos/EvenAR/node-simconnect/git/blobs{/sha}",
  "git_tags_url": "https://api.github.com/repos/EvenAR/node-simconnect/git/tags{/sha}",
  "git_refs_url": "https://api.github.com/repos/EvenAR/node-simconnect/git/refs{/sha}",
  "trees_url": "https://api.github.com/repos/EvenAR/node-simconnect/git/trees{/sha}",
  "statuses_url": "https://api.github.com/repos/EvenAR/node-simconnect/statuses/{sha}",
  "languages_url": "https://api.github.com/repos/EvenAR/node-simconnect/languages",
  "stargazers_url": "https://api.github.com/repos/EvenAR/node-simconnect/stargazers",
  "contributors_url": "https://api.github.com/repos/EvenAR/node-simconnect/contributors",
  "subscribers_url": "https://api.github.com/repos/EvenAR/node-simconnect/subscribers",
  "subscription_url": "https://api.github.com/repos/EvenAR/node-simconnect/subscription",
  "commits_url": "https://api.github.com/repos/EvenAR/node-simconnect/commits{/sha}",
  "git_commits_url": "https://api.github.com/repos/EvenAR/node-simconnect/git/commits{/sha}",
  "comments_url": "https://api.github.com/repos/EvenAR/node-simconnect/comments{/number}",
  "issue_comment_url": "https://api.github.com/repos/EvenAR/node-simconnect/issues/comments{/number}",
  "contents_url": "https://api.github.com/repos/EvenAR/node-simconnect/contents/{+path}",
  "compare_url": "https://api.github.com/repos/EvenAR/node-simconnect/compare/{base}...{head}",
  "merges_url": "https://api.github.com/repos/EvenAR/node-simconnect/merges",
  "archive_url": "https://api.github.com/repos/EvenAR/node-simconnect/{archive_format}{/ref}",
  "downloads_url": "https://api.github.com/repos/EvenAR/node-simconnect/downloads",
  "issues_url": "https://api.github.com/repos/EvenAR/node-simconnect/issues{/number}",
  "pulls_url": "https://api.github.com/repos/EvenAR/node-simconnect/pulls{/number}",
  "milestones_url": "https://api.github.com/repos/EvenAR/node-simconnect/milestones{/number}",
  "notifications_url": "https://api.github.com/repos/EvenAR/node-simconnect/notifications{?since,all,participating}",
  "labels_url": "https://api.github.com/repos/EvenAR/node-simconnect/labels{/name}",
  "releases_url": "https://api.github.com/repos/EvenAR/node-simconnect/releases{/id}",
  "deployments_url": "https://api.github.com/repos/EvenAR/node-simconnect/deployments",
  "created_at": "2017-07-21T09:20:36Z",
  "updated_at": "2025-07-27T16:10:52Z",
  "pushed_at": "2025-02-12T21:36:56Z",
  "git_url": "git://github.com/EvenAR/node-simconnect.git",
  "ssh_url": "git@github.com:EvenAR/node-simconnect.git",
  "clone_url": "https://github.com/EvenAR/node-simconnect.git",
  "svn_url": "https://github.com/EvenAR/node-simconnect",
  "homepage": "",
  "size": 43000,
  "stargazers_count": 107,
  "watchers_count": 107,
  "language": "TypeScript",
  "has_issues": true,
  "has_projects": true,
  "has_downloads": true,
  "has_wiki": true,
  "has_pages": true,
  "has_discussions": true,
  "forks_count": 33,
  "mirror_url": null,
  "archived": false,
  "disabled": false,
  "open_issues_count": 3,
  "license": {
    "key": "lgpl-3.0",
    "name": "GNU Lesser General Public License v3.0",
    "spdx_id": "LGPL-3.0",
    "url": "https://api.github.com/licenses/lgpl-3.0",
    "node_id": "MDc6TGljZW5zZTEy"
  },
  "allow_forking": true,
  "is_template": false,
  "web_commit_signoff_required": false,
  "topics": [
    "flight-simulation",
    "flightsim",
    "fsx",
    "gaming",
    "microsoft-flight-simulator",
    "msfs",
    "msfs2020",
    "prepar3d",
    "sdk",
    "simconnect",
    "virtual-airline"
  ],
  "visibility": "public",
  "forks": 33,
  "open_issues": 3,
  "watchers": 107,
  "default_branch": "master",
  "permissions": {
    "admin": false,
    "maintain": false,
    "push": false,
    "triage": false,
    "pull": true
  },
  "score": 1.0
}