{
  "id": 2696306,
  "node_id": "MDEwOlJlcG9zaXRvcnkyNjk2MzA2",
  "name": "Remmina",
  "full_name": "FreeRDP/Remmina",
  "private": false,
  "owner": {
    "login": "FreeRDP",
    "id": 663376,
    "node_id": "MDEyOk9yZ2FuaXphdGlvbjY2MzM3Ng==",
    "avatar_url": "https://avatars.githubusercontent.com/u/663376?v=4",
    "gravatar_id": "",
    "url": "https://api.github.com/users/FreeRDP",
    "html_url": "https://github.com/FreeRDP",
    "followers_url": "https://api.github.com/users/FreeRDP/followers",
    "following_url": "https://api.github.com/users/FreeRDP/following{/other_user}",
    "gists_url": "https://api.github.com/users/FreeRDP/gists{/gist_id}",
    "starred_url": "https://api.github.com/users/FreeRDP/starred{/owner}{/repo}",
    "subscriptions_url": "https://api.github.com/users/FreeRDP/subscriptions",
    "organizations_url": "https://api.github.com/users/FreeRDP/orgs",
    "repos_url": "https://api.github.com/users/FreeRDP/repos",
    "events_url": "https://api.github.com/users/FreeRDP/events{/privacy}",
    "received_events_url": "https://api.github.com/users/FreeRDP/received_events",
    "type": "Organization",
    "user_view_type": "public",
    "site_admin": false
  },
  "html_url": "https://github.com/FreeRDP/Remmina",
  "description": "Mirror of https://gitlab.com/Remmina/Remmina The GTK+ Remmina Remote Desktop Client",
  "fork": false,
  "url": "https://api.github.com/repos/FreeRDP/Remmina",
  "forks_url": "https://api.github.com/repos/FreeRDP/Remmina/forks",
  "keys_url": "https://api.github.com/repos/FreeRDP/Remmina/keys{/key_id}",
  "collaborators_url": "https://api.github.com/repos/FreeRDP/Remmina/collaborators{/collaborator}",
  "teams_url": "https://api.github.com/repos/FreeRDP/Remmina/teams",
  "hooks_url": "https://api.github.com/repos/FreeRDP/Remmina/hooks",
  "issue_events_url": "https://api.github.com/repos/FreeRDP/Remmina/issues/events{/number}",
  "events_url": "https://api.github.com/repos/FreeRDP/Remmina/events",
  "assignees_url": "https://api.github.com/repos/FreeRDP/Remmina/assignees{/user}",
  "branches_url": "https://api.github.com/repos/FreeRDP/Remmina/branches{/branch}",
  "tags_url": "https://api.github.com/repos/FreeRDP/Remmina/tags",
  "blobs_url": "https://api.github.com/repos/FreeRDP/Remmina/git/blobs{/sha}",
  "git_tags_url": "https://api.github.com/repos/FreeRDP/Remmina/git/tags{/sha}",
  "git_refs_url": "https://api.github.com/repos/FreeRDP/Remmina/git/refs{/sha}",
  "trees_url": "https://api.github.com/repos/FreeRDP/Remmina/git/trees{/sha}",
  "statuses_url": "https://api.github.com/repos/FreeRDP/Remmina/statuses/{sha}",
  "languages_url": "https://api.github.com/repos/FreeRDP/Remmina/languages",
  "stargazers_url": "https://api.github.com/repos/FreeRDP/Remmina/stargazers",
  "contributors_url": "https://api.github.com/repos/FreeRDP/Remmina/contributors",
  "subscribers_url": "https://api.github.com/repos/FreeRDP/Remmina/subscribers",
  "subscription_url": "https://api.github.com/repos/FreeRDP/Remmina/subscription",
  "commits_url": "https://api.github.com/repos/FreeRDP/Remmina/commits{/sha}",
  "git_commits_url": "https://api.github.com/repos/FreeRDP/Remmina/git/commits{/sha}",
  "comments_url": "https://api.github.com/repos/FreeRDP/Remmina/comments{/number}",
  "issue_comment_url": "https://api.github.com/repos/FreeRDP/Remmina/issues/comments{/number}",
  "contents_url": "https://api.github.com/repos/FreeRDP/Remmina/contents/{+path}",
  "compare_url": "https://api.github.com/repos/FreeRDP/Remmina/compare/{base}...{head}",
  "merges_url": "https://api.github.com/repos/FreeRDP/Remmina/merges",
  "archive_url": "https://api.github.com/repos/FreeRDP/Remmina/{archive_format}{/ref}",
  "downloads_url": "https://api.github.com/repos/FreeRDP/Remmina/downloads",
  "issues_url": "https://api.github.com/repos/FreeRDP/Remmina/issues{/number}",
  "pulls_url": "https://api.github.com/repos/FreeRDP/Remmina/pulls{/number}",
  "milestones_url": "https://api.github.com/repos/FreeRDP/Remmina/milestones{/number}",
  "notifications_url": "https://api.github.com/repos/FreeRDP/Remmina/notifications{?since,all,participating}",
  "labels_url": "https://api.github.com/repos/FreeRDP/Remmina/labels{/name}",
  "releases_url": "https://api.github.com/repos/FreeRDP/Remmina/releases{/id}",
  "deployments_url": "https://api.github.com/repos/FreeRDP/Remmina/deployments",
  "created_at": "2011-11-02T16:33:50Z",
  "updated_at": "2025-08-04T17:34:24Z",
  "pushed_at": "2025-08-04T13:03:16Z",
  "git_url": "git://github.com/FreeRDP/Remmina.git",
  "ssh_url": "git@github.com:FreeRDP/Remmina.git",
  "clone_url": "https://github.com/FreeRDP/Remmina.git",
  "svn_url": "https://github.com/FreeRDP/Remmina",
  "homepage": "http://remmina.org",
  "size": 426315,
  "stargazers_count": 2350,
  "watchers_count": 2350,
  "language": "C",
  "has_issues": false,
  "has_projects": false,
  "has_downloads": true,
  "has_wiki": true,
  "has_pages": false,
  "has_discussions": false,
  "forks_count": 600,
  "mirror_url": null,
  "archived": false,
  "disabled": false,
  "open_issues_count": 334,
  "license": {
    "key": "gpl-2.0",
    "name": "GNU General Public License v2.0",
    "spdx_id": "GPL-2.0",
    "url": "https://api.github.com/licenses/gpl-2.0",
    "node_id": "MDc6TGljZW5zZTg="
  },
  "allow_forking": true,
  "is_template": false,
  "web_commit_signoff_required": false,
  "topics": [
    "gtk",
    "rdp",
    "remote-control",
    "spice",
    "ssh-client",
    "vnc"
  ],
  "visibility": "public",
  "forks": 600,
  "open_issues": 334,
  "watchers": 2350,
  "default_branch": "master",
  "permissions": {
    "admin": false,
    "maintain": false,
    "push": false,
    "triage": false,
    "pull": true
  },
  "score": 1.0
}