{
  "id": 123819721,
  "node_id": "MDEwOlJlcG9zaXRvcnkxMjM4MTk3MjE=",
  "name": "jsgam",
  "full_name": "kreezii/jsgam",
  "private": false,
  "owner": {
    "login": "kreezii",
    "id": 37048758,
    "node_id": "MDQ6VXNlcjM3MDQ4NzU4",
    "avatar_url": "https://avatars.githubusercontent.com/u/37048758?v=4",
    "gravatar_id": "",
    "url": "https://api.github.com/users/kreezii",
    "html_url": "https://github.com/kreezii",
    "followers_url": "https://api.github.com/users/kreezii/followers",
    "following_url": "https://api.github.com/users/kreezii/following{/other_user}",
    "gists_url": "https://api.github.com/users/kreezii/gists{/gist_id}",
    "starred_url": "https://api.github.com/users/kreezii/starred{/owner}{/repo}",
    "subscriptions_url": "https://api.github.com/users/kreezii/subscriptions",
    "organizations_url": "https://api.github.com/users/kreezii/orgs",
    "repos_url": "https://api.github.com/users/kreezii/repos",
    "events_url": "https://api.github.com/users/kreezii/events{/privacy}",
    "received_events_url": "https://api.github.com/users/kreezii/received_events",
    "type": "User",
    "user_view_type": "public",
    "site_admin": false
  },
  "html_url": "https://github.com/kreezii/jsgam",
  "description": "JavaScript Adventure Game Maker: Point and click/touch game adventures engine!",
  "fork": false,
  "url": "https://api.github.com/repos/kreezii/jsgam",
  "forks_url": "https://api.github.com/repos/kreezii/jsgam/forks",
  "keys_url": "https://api.github.com/repos/kreezii/jsgam/keys{/key_id}",
  "collaborators_url": "https://api.github.com/repos/kreezii/jsgam/collaborators{/collaborator}",
  "teams_url": "https://api.github.com/repos/kreezii/jsgam/teams",
  "hooks_url": "https://api.github.com/repos/kreezii/jsgam/hooks",
  "issue_events_url": "https://api.github.com/repos/kreezii/jsgam/issues/events{/number}",
  "events_url": "https://api.github.com/repos/kreezii/jsgam/events",
  "assignees_url": "https://api.github.com/repos/kreezii/jsgam/assignees{/user}",
  "branches_url": "https://api.github.com/repos/kreezii/jsgam/branches{/branch}",
  "tags_url": "https://api.github.com/repos/kreezii/jsgam/tags",
  "blobs_url": "https://api.github.com/repos/kreezii/jsgam/git/blobs{/sha}",
  "git_tags_url": "https://api.github.com/repos/kreezii/jsgam/git/tags{/sha}",
  "git_refs_url": "https://api.github.com/repos/kreezii/jsgam/git/refs{/sha}",
  "trees_url": "https://api.github.com/repos/kreezii/jsgam/git/trees{/sha}",
  "statuses_url": "https://api.github.com/repos/kreezii/jsgam/statuses/{sha}",
  "languages_url": "https://api.github.com/repos/kreezii/jsgam/languages",
  "stargazers_url": "https://api.github.com/repos/kreezii/jsgam/stargazers",
  "contributors_url": "https://api.github.com/repos/kreezii/jsgam/contributors",
  "subscribers_url": "https://api.github.com/repos/kreezii/jsgam/subscribers",
  "subscription_url": "https://api.github.com/repos/kreezii/jsgam/subscription",
  "commits_url": "https://api.github.com/repos/kreezii/jsgam/commits{/sha}",
  "git_commits_url": "https://api.github.com/repos/kreezii/jsgam/git/commits{/sha}",
  "comments_url": "https://api.github.com/repos/kreezii/jsgam/comments{/number}",
  "issue_comment_url": "https://api.github.com/repos/kreezii/jsgam/issues/comments{/number}",
  "contents_url": "https://api.github.com/repos/kreezii/jsgam/contents/{+path}",
  "compare_url": "https://api.github.com/repos/kreezii/jsgam/compare/{base}...{head}",
  "merges_url": "https://api.github.com/repos/kreezii/jsgam/merges",
  "archive_url": "https://api.github.com/repos/kreezii/jsgam/{archive_format}{/ref}",
  "downloads_url": "https://api.github.com/repos/kreezii/jsgam/downloads",
  "issues_url": "https://api.github.com/repos/kreezii/jsgam/issues{/number}",
  "pulls_url": "https://api.github.com/repos/kreezii/jsgam/pulls{/number}",
  "milestones_url": "https://api.github.com/repos/kreezii/jsgam/milestones{/number}",
  "notifications_url": "https://api.github.com/repos/kreezii/jsgam/notifications{?since,all,participating}",
  "labels_url": "https://api.github.com/repos/kreezii/jsgam/labels{/name}",
  "releases_url": "https://api.github.com/repos/kreezii/jsgam/releases{/id}",
  "deployments_url": "https://api.github.com/repos/kreezii/jsgam/deployments",
  "created_at": "2018-03-04T19:07:45Z",
  "updated_at": "2025-05-03T15:01:40Z",
  "pushed_at": "2025-04-27T00:45:32Z",
  "git_url": "git://github.com/kreezii/jsgam.git",
  "ssh_url": "git@github.com:kreezii/jsgam.git",
  "clone_url": "https://github.com/kreezii/jsgam.git",
  "svn_url": "https://github.com/kreezii/jsgam",
  "homepage": "https://kreezii.github.io/jsgam/",
  "size": 31654,
  "stargazers_count": 76,
  "watchers_count": 76,
  "language": "JavaScript",
  "has_issues": true,
  "has_projects": true,
  "has_downloads": true,
  "has_wiki": true,
  "has_pages": true,
  "has_discussions": false,
  "forks_count": 12,
  "mirror_url": null,
  "archived": false,
  "disabled": false,
  "open_issues_count": 4,
  "license": {
    "key": "mit",
    "name": "MIT License",
    "spdx_id": "MIT",
    "url": "https://api.github.com/licenses/mit",
    "node_id": "MDc6TGljZW5zZTEz"
  },
  "allow_forking": true,
  "is_template": false,
  "web_commit_signoff_required": false,
  "topics": [
    "game-engine"
  ],
  "visibility": "public",
  "forks": 12,
  "open_issues": 4,
  "watchers": 76,
  "default_branch": "master",
  "permissions": {
    "admin": false,
    "maintain": false,
    "push": false,
    "triage": false,
    "pull": true
  },
  "score": 1.0
}