{
  "id": 5099405,
  "node_id": "MDEwOlJlcG9zaXRvcnk1MDk5NDA1",
  "name": "nemo",
  "full_name": "linuxmint/nemo",
  "private": false,
  "owner": {
    "login": "linuxmint",
    "id": 107184,
    "node_id": "MDEyOk9yZ2FuaXphdGlvbjEwNzE4NA==",
    "avatar_url": "https://avatars.githubusercontent.com/u/107184?v=4",
    "gravatar_id": "",
    "url": "https://api.github.com/users/linuxmint",
    "html_url": "https://github.com/linuxmint",
    "followers_url": "https://api.github.com/users/linuxmint/followers",
    "following_url": "https://api.github.com/users/linuxmint/following{/other_user}",
    "gists_url": "https://api.github.com/users/linuxmint/gists{/gist_id}",
    "starred_url": "https://api.github.com/users/linuxmint/starred{/owner}{/repo}",
    "subscriptions_url": "https://api.github.com/users/linuxmint/subscriptions",
    "organizations_url": "https://api.github.com/users/linuxmint/orgs",
    "repos_url": "https://api.github.com/users/linuxmint/repos",
    "events_url": "https://api.github.com/users/linuxmint/events{/privacy}",
    "received_events_url": "https://api.github.com/users/linuxmint/received_events",
    "type": "Organization",
    "user_view_type": "public",
    "site_admin": false
  },
  "html_url": "https://github.com/linuxmint/nemo",
  "description": "File browser for Cinnamon",
  "fork": false,
  "url": "https://api.github.com/repos/linuxmint/nemo",
  "forks_url": "https://api.github.com/repos/linuxmint/nemo/forks",
  "keys_url": "https://api.github.com/repos/linuxmint/nemo/keys{/key_id}",
  "collaborators_url": "https://api.github.com/repos/linuxmint/nemo/collaborators{/collaborator}",
  "teams_url": "https://api.github.com/repos/linuxmint/nemo/teams",
  "hooks_url": "https://api.github.com/repos/linuxmint/nemo/hooks",
  "issue_events_url": "https://api.github.com/repos/linuxmint/nemo/issues/events{/number}",
  "events_url": "https://api.github.com/repos/linuxmint/nemo/events",
  "assignees_url": "https://api.github.com/repos/linuxmint/nemo/assignees{/user}",
  "branches_url": "https://api.github.com/repos/linuxmint/nemo/branches{/branch}",
  "tags_url": "https://api.github.com/repos/linuxmint/nemo/tags",
  "blobs_url": "https://api.github.com/repos/linuxmint/nemo/git/blobs{/sha}",
  "git_tags_url": "https://api.github.com/repos/linuxmint/nemo/git/tags{/sha}",
  "git_refs_url": "https://api.github.com/repos/linuxmint/nemo/git/refs{/sha}",
  "trees_url": "https://api.github.com/repos/linuxmint/nemo/git/trees{/sha}",
  "statuses_url": "https://api.github.com/repos/linuxmint/nemo/statuses/{sha}",
  "languages_url": "https://api.github.com/repos/linuxmint/nemo/languages",
  "stargazers_url": "https://api.github.com/repos/linuxmint/nemo/stargazers",
  "contributors_url": "https://api.github.com/repos/linuxmint/nemo/contributors",
  "subscribers_url": "https://api.github.com/repos/linuxmint/nemo/subscribers",
  "subscription_url": "https://api.github.com/repos/linuxmint/nemo/subscription",
  "commits_url": "https://api.github.com/repos/linuxmint/nemo/commits{/sha}",
  "git_commits_url": "https://api.github.com/repos/linuxmint/nemo/git/commits{/sha}",
  "comments_url": "https://api.github.com/repos/linuxmint/nemo/comments{/number}",
  "issue_comment_url": "https://api.github.com/repos/linuxmint/nemo/issues/comments{/number}",
  "contents_url": "https://api.github.com/repos/linuxmint/nemo/contents/{+path}",
  "compare_url": "https://api.github.com/repos/linuxmint/nemo/compare/{base}...{head}",
  "merges_url": "https://api.github.com/repos/linuxmint/nemo/merges",
  "archive_url": "https://api.github.com/repos/linuxmint/nemo/{archive_format}{/ref}",
  "downloads_url": "https://api.github.com/repos/linuxmint/nemo/downloads",
  "issues_url": "https://api.github.com/repos/linuxmint/nemo/issues{/number}",
  "pulls_url": "https://api.github.com/repos/linuxmint/nemo/pulls{/number}",
  "milestones_url": "https://api.github.com/repos/linuxmint/nemo/milestones{/number}",
  "notifications_url": "https://api.github.com/repos/linuxmint/nemo/notifications{?since,all,participating}",
  "labels_url": "https://api.github.com/repos/linuxmint/nemo/labels{/name}",
  "releases_url": "https://api.github.com/repos/linuxmint/nemo/releases{/id}",
  "deployments_url": "https://api.github.com/repos/linuxmint/nemo/deployments",
  "created_at": "2012-07-18T17:22:28Z",
  "updated_at": "2025-08-03T13:20:51Z",
  "pushed_at": "2025-07-26T16:54:30Z",
  "git_url": "git://github.com/linuxmint/nemo.git",
  "ssh_url": "git@github.com:linuxmint/nemo.git",
  "clone_url": "https://github.com/linuxmint/nemo.git",
  "svn_url": "https://github.com/linuxmint/nemo",
  "homepage": null,
  "size": 19927,
  "stargazers_count": 1361,
  "watchers_count": 1361,
  "language": "C",
  "has_issues": true,
  "has_projects": false,
  "has_downloads": true,
  "has_wiki": true,
  "has_pages": false,
  "has_discussions": false,
  "forks_count": 317,
  "mirror_url": null,
  "archived": false,
  "disabled": false,
  "open_issues_count": 770,
  "license": {
    "key": "gpl-2.0",
    "name": "GNU General Public License v2.0",
    "spdx_id": "GPL-2.0",
    "url": "https://api.github.com/licenses/gpl-2.0",
    "node_id": "MDc6TGljZW5zZTg="
  },
  "allow_forking": true,
  "is_template": false,
  "web_commit_signoff_required": false,
  "topics": [],
  "visibility": "public",
  "forks": 317,
  "open_issues": 770,
  "watchers": 1361,
  "default_branch": "master",
  "permissions": {
    "admin": false,
    "maintain": false,
    "push": false,
    "triage": false,
    "pull": true
  },
  "score": 1.0
}