{
  "id": 457231862,
  "node_id": "R_kgDOG0DN9g",
  "name": "graphite",
  "full_name": "netreplica/graphite",
  "private": false,
  "owner": {
    "login": "netreplica",
    "id": 98500029,
    "node_id": "O_kgDOBd79vQ",
    "avatar_url": "https://avatars.githubusercontent.com/u/98500029?v=4",
    "gravatar_id": "",
    "url": "https://api.github.com/users/netreplica",
    "html_url": "https://github.com/netreplica",
    "followers_url": "https://api.github.com/users/netreplica/followers",
    "following_url": "https://api.github.com/users/netreplica/following{/other_user}",
    "gists_url": "https://api.github.com/users/netreplica/gists{/gist_id}",
    "starred_url": "https://api.github.com/users/netreplica/starred{/owner}{/repo}",
    "subscriptions_url": "https://api.github.com/users/netreplica/subscriptions",
    "organizations_url": "https://api.github.com/users/netreplica/orgs",
    "repos_url": "https://api.github.com/users/netreplica/repos",
    "events_url": "https://api.github.com/users/netreplica/events{/privacy}",
    "received_events_url": "https://api.github.com/users/netreplica/received_events",
    "type": "Organization",
    "user_view_type": "public",
    "site_admin": false
  },
  "html_url": "https://github.com/netreplica/graphite",
  "description": "Visualization for Network Topologies – NetBox, Containerlab, Netlab",
  "fork": false,
  "url": "https://api.github.com/repos/netreplica/graphite",
  "forks_url": "https://api.github.com/repos/netreplica/graphite/forks",
  "keys_url": "https://api.github.com/repos/netreplica/graphite/keys{/key_id}",
  "collaborators_url": "https://api.github.com/repos/netreplica/graphite/collaborators{/collaborator}",
  "teams_url": "https://api.github.com/repos/netreplica/graphite/teams",
  "hooks_url": "https://api.github.com/repos/netreplica/graphite/hooks",
  "issue_events_url": "https://api.github.com/repos/netreplica/graphite/issues/events{/number}",
  "events_url": "https://api.github.com/repos/netreplica/graphite/events",
  "assignees_url": "https://api.github.com/repos/netreplica/graphite/assignees{/user}",
  "branches_url": "https://api.github.com/repos/netreplica/graphite/branches{/branch}",
  "tags_url": "https://api.github.com/repos/netreplica/graphite/tags",
  "blobs_url": "https://api.github.com/repos/netreplica/graphite/git/blobs{/sha}",
  "git_tags_url": "https://api.github.com/repos/netreplica/graphite/git/tags{/sha}",
  "git_refs_url": "https://api.github.com/repos/netreplica/graphite/git/refs{/sha}",
  "trees_url": "https://api.github.com/repos/netreplica/graphite/git/trees{/sha}",
  "statuses_url": "https://api.github.com/repos/netreplica/graphite/statuses/{sha}",
  "languages_url": "https://api.github.com/repos/netreplica/graphite/languages",
  "stargazers_url": "https://api.github.com/repos/netreplica/graphite/stargazers",
  "contributors_url": "https://api.github.com/repos/netreplica/graphite/contributors",
  "subscribers_url": "https://api.github.com/repos/netreplica/graphite/subscribers",
  "subscription_url": "https://api.github.com/repos/netreplica/graphite/subscription",
  "commits_url": "https://api.github.com/repos/netreplica/graphite/commits{/sha}",
  "git_commits_url": "https://api.github.com/repos/netreplica/graphite/git/commits{/sha}",
  "comments_url": "https://api.github.com/repos/netreplica/graphite/comments{/number}",
  "issue_comment_url": "https://api.github.com/repos/netreplica/graphite/issues/comments{/number}",
  "contents_url": "https://api.github.com/repos/netreplica/graphite/contents/{+path}",
  "compare_url": "https://api.github.com/repos/netreplica/graphite/compare/{base}...{head}",
  "merges_url": "https://api.github.com/repos/netreplica/graphite/merges",
  "archive_url": "https://api.github.com/repos/netreplica/graphite/{archive_format}{/ref}",
  "downloads_url": "https://api.github.com/repos/netreplica/graphite/downloads",
  "issues_url": "https://api.github.com/repos/netreplica/graphite/issues{/number}",
  "pulls_url": "https://api.github.com/repos/netreplica/graphite/pulls{/number}",
  "milestones_url": "https://api.github.com/repos/netreplica/graphite/milestones{/number}",
  "notifications_url": "https://api.github.com/repos/netreplica/graphite/notifications{?since,all,participating}",
  "labels_url": "https://api.github.com/repos/netreplica/graphite/labels{/name}",
  "releases_url": "https://api.github.com/repos/netreplica/graphite/releases{/id}",
  "deployments_url": "https://api.github.com/repos/netreplica/graphite/deployments",
  "created_at": "2022-02-09T06:11:26Z",
  "updated_at": "2025-07-29T06:56:40Z",
  "pushed_at": "2025-08-02T18:25:31Z",
  "git_url": "git://github.com/netreplica/graphite.git",
  "ssh_url": "git@github.com:netreplica/graphite.git",
  "clone_url": "https://github.com/netreplica/graphite.git",
  "svn_url": "https://github.com/netreplica/graphite",
  "homepage": "https://netreplica.com",
  "size": 2971,
  "stargazers_count": 78,
  "watchers_count": 78,
  "language": "JavaScript",
  "has_issues": true,
  "has_projects": true,
  "has_downloads": true,
  "has_wiki": true,
  "has_pages": false,
  "has_discussions": false,
  "forks_count": 6,
  "mirror_url": null,
  "archived": false,
  "disabled": false,
  "open_issues_count": 25,
  "license": {
    "key": "apache-2.0",
    "name": "Apache License 2.0",
    "spdx_id": "Apache-2.0",
    "url": "https://api.github.com/licenses/apache-2.0",
    "node_id": "MDc6TGljZW5zZTI="
  },
  "allow_forking": true,
  "is_template": false,
  "web_commit_signoff_required": false,
  "topics": [
    "containerlab",
    "netbox",
    "networking",
    "nextui",
    "visualization"
  ],
  "visibility": "public",
  "forks": 6,
  "open_issues": 25,
  "watchers": 78,
  "default_branch": "main",
  "permissions": {
    "admin": false,
    "maintain": false,
    "push": false,
    "triage": false,
    "pull": true
  },
  "score": 1.0
}