{
  "id": 392073567,
  "node_id": "MDEwOlJlcG9zaXRvcnkzOTIwNzM1Njc=",
  "name": "docs",
  "full_name": "open-sauced/docs",
  "private": false,
  "owner": {
    "login": "open-sauced",
    "id": 57568598,
    "node_id": "MDEyOk9yZ2FuaXphdGlvbjU3NTY4NTk4",
    "avatar_url": "https://avatars.githubusercontent.com/u/57568598?v=4",
    "gravatar_id": "",
    "url": "https://api.github.com/users/open-sauced",
    "html_url": "https://github.com/open-sauced",
    "followers_url": "https://api.github.com/users/open-sauced/followers",
    "following_url": "https://api.github.com/users/open-sauced/following{/other_user}",
    "gists_url": "https://api.github.com/users/open-sauced/gists{/gist_id}",
    "starred_url": "https://api.github.com/users/open-sauced/starred{/owner}{/repo}",
    "subscriptions_url": "https://api.github.com/users/open-sauced/subscriptions",
    "organizations_url": "https://api.github.com/users/open-sauced/orgs",
    "repos_url": "https://api.github.com/users/open-sauced/repos",
    "events_url": "https://api.github.com/users/open-sauced/events{/privacy}",
    "received_events_url": "https://api.github.com/users/open-sauced/received_events",
    "type": "Organization",
    "user_view_type": "public",
    "site_admin": false
  },
  "html_url": "https://github.com/open-sauced/docs",
  "description": "OpenSauced documentation built with docusaurus",
  "fork": false,
  "url": "https://api.github.com/repos/open-sauced/docs",
  "forks_url": "https://api.github.com/repos/open-sauced/docs/forks",
  "keys_url": "https://api.github.com/repos/open-sauced/docs/keys{/key_id}",
  "collaborators_url": "https://api.github.com/repos/open-sauced/docs/collaborators{/collaborator}",
  "teams_url": "https://api.github.com/repos/open-sauced/docs/teams",
  "hooks_url": "https://api.github.com/repos/open-sauced/docs/hooks",
  "issue_events_url": "https://api.github.com/repos/open-sauced/docs/issues/events{/number}",
  "events_url": "https://api.github.com/repos/open-sauced/docs/events",
  "assignees_url": "https://api.github.com/repos/open-sauced/docs/assignees{/user}",
  "branches_url": "https://api.github.com/repos/open-sauced/docs/branches{/branch}",
  "tags_url": "https://api.github.com/repos/open-sauced/docs/tags",
  "blobs_url": "https://api.github.com/repos/open-sauced/docs/git/blobs{/sha}",
  "git_tags_url": "https://api.github.com/repos/open-sauced/docs/git/tags{/sha}",
  "git_refs_url": "https://api.github.com/repos/open-sauced/docs/git/refs{/sha}",
  "trees_url": "https://api.github.com/repos/open-sauced/docs/git/trees{/sha}",
  "statuses_url": "https://api.github.com/repos/open-sauced/docs/statuses/{sha}",
  "languages_url": "https://api.github.com/repos/open-sauced/docs/languages",
  "stargazers_url": "https://api.github.com/repos/open-sauced/docs/stargazers",
  "contributors_url": "https://api.github.com/repos/open-sauced/docs/contributors",
  "subscribers_url": "https://api.github.com/repos/open-sauced/docs/subscribers",
  "subscription_url": "https://api.github.com/repos/open-sauced/docs/subscription",
  "commits_url": "https://api.github.com/repos/open-sauced/docs/commits{/sha}",
  "git_commits_url": "https://api.github.com/repos/open-sauced/docs/git/commits{/sha}",
  "comments_url": "https://api.github.com/repos/open-sauced/docs/comments{/number}",
  "issue_comment_url": "https://api.github.com/repos/open-sauced/docs/issues/comments{/number}",
  "contents_url": "https://api.github.com/repos/open-sauced/docs/contents/{+path}",
  "compare_url": "https://api.github.com/repos/open-sauced/docs/compare/{base}...{head}",
  "merges_url": "https://api.github.com/repos/open-sauced/docs/merges",
  "archive_url": "https://api.github.com/repos/open-sauced/docs/{archive_format}{/ref}",
  "downloads_url": "https://api.github.com/repos/open-sauced/docs/downloads",
  "issues_url": "https://api.github.com/repos/open-sauced/docs/issues{/number}",
  "pulls_url": "https://api.github.com/repos/open-sauced/docs/pulls{/number}",
  "milestones_url": "https://api.github.com/repos/open-sauced/docs/milestones{/number}",
  "notifications_url": "https://api.github.com/repos/open-sauced/docs/notifications{?since,all,participating}",
  "labels_url": "https://api.github.com/repos/open-sauced/docs/labels{/name}",
  "releases_url": "https://api.github.com/repos/open-sauced/docs/releases{/id}",
  "deployments_url": "https://api.github.com/repos/open-sauced/docs/deployments",
  "created_at": "2021-08-02T19:40:54Z",
  "updated_at": "2025-07-09T22:18:03Z",
  "pushed_at": "2025-08-03T00:22:22Z",
  "git_url": "git://github.com/open-sauced/docs.git",
  "ssh_url": "git@github.com:open-sauced/docs.git",
  "clone_url": "https://github.com/open-sauced/docs.git",
  "svn_url": "https://github.com/open-sauced/docs",
  "homepage": "http://opensauced.pizza/docs",
  "size": 120757,
  "stargazers_count": 87,
  "watchers_count": 87,
  "language": "JavaScript",
  "has_issues": true,
  "has_projects": true,
  "has_downloads": true,
  "has_wiki": true,
  "has_pages": true,
  "has_discussions": true,
  "forks_count": 62,
  "mirror_url": null,
  "archived": false,
  "disabled": false,
  "open_issues_count": 28,
  "license": {
    "key": "mit",
    "name": "MIT License",
    "spdx_id": "MIT",
    "url": "https://api.github.com/licenses/mit",
    "node_id": "MDc6TGljZW5zZTEz"
  },
  "allow_forking": true,
  "is_template": false,
  "web_commit_signoff_required": false,
  "topics": [
    "docs",
    "docusaurus",
    "hacktoberfest",
    "insights"
  ],
  "visibility": "public",
  "forks": 62,
  "open_issues": 28,
  "watchers": 87,
  "default_branch": "main",
  "permissions": {
    "admin": false,
    "maintain": false,
    "push": false,
    "triage": false,
    "pull": true
  },
  "score": 1.0
}