{
  "id": 416656992,
  "node_id": "R_kgDOGNWuYA",
  "name": "ext-openswoole",
  "full_name": "openswoole/ext-openswoole",
  "private": false,
  "owner": {
    "login": "openswoole",
    "id": 89640194,
    "node_id": "MDEyOk9yZ2FuaXphdGlvbjg5NjQwMTk0",
    "avatar_url": "https://avatars.githubusercontent.com/u/89640194?v=4",
    "gravatar_id": "",
    "url": "https://api.github.com/users/openswoole",
    "html_url": "https://github.com/openswoole",
    "followers_url": "https://api.github.com/users/openswoole/followers",
    "following_url": "https://api.github.com/users/openswoole/following{/other_user}",
    "gists_url": "https://api.github.com/users/openswoole/gists{/gist_id}",
    "starred_url": "https://api.github.com/users/openswoole/starred{/owner}{/repo}",
    "subscriptions_url": "https://api.github.com/users/openswoole/subscriptions",
    "organizations_url": "https://api.github.com/users/openswoole/orgs",
    "repos_url": "https://api.github.com/users/openswoole/repos",
    "events_url": "https://api.github.com/users/openswoole/events{/privacy}",
    "received_events_url": "https://api.github.com/users/openswoole/received_events",
    "type": "Organization",
    "user_view_type": "public",
    "site_admin": false
  },
  "html_url": "https://github.com/openswoole/ext-openswoole",
  "description": "Programmatic server for PHP with async IO, coroutines and fibers",
  "fork": false,
  "url": "https://api.github.com/repos/openswoole/ext-openswoole",
  "forks_url": "https://api.github.com/repos/openswoole/ext-openswoole/forks",
  "keys_url": "https://api.github.com/repos/openswoole/ext-openswoole/keys{/key_id}",
  "collaborators_url": "https://api.github.com/repos/openswoole/ext-openswoole/collaborators{/collaborator}",
  "teams_url": "https://api.github.com/repos/openswoole/ext-openswoole/teams",
  "hooks_url": "https://api.github.com/repos/openswoole/ext-openswoole/hooks",
  "issue_events_url": "https://api.github.com/repos/openswoole/ext-openswoole/issues/events{/number}",
  "events_url": "https://api.github.com/repos/openswoole/ext-openswoole/events",
  "assignees_url": "https://api.github.com/repos/openswoole/ext-openswoole/assignees{/user}",
  "branches_url": "https://api.github.com/repos/openswoole/ext-openswoole/branches{/branch}",
  "tags_url": "https://api.github.com/repos/openswoole/ext-openswoole/tags",
  "blobs_url": "https://api.github.com/repos/openswoole/ext-openswoole/git/blobs{/sha}",
  "git_tags_url": "https://api.github.com/repos/openswoole/ext-openswoole/git/tags{/sha}",
  "git_refs_url": "https://api.github.com/repos/openswoole/ext-openswoole/git/refs{/sha}",
  "trees_url": "https://api.github.com/repos/openswoole/ext-openswoole/git/trees{/sha}",
  "statuses_url": "https://api.github.com/repos/openswoole/ext-openswoole/statuses/{sha}",
  "languages_url": "https://api.github.com/repos/openswoole/ext-openswoole/languages",
  "stargazers_url": "https://api.github.com/repos/openswoole/ext-openswoole/stargazers",
  "contributors_url": "https://api.github.com/repos/openswoole/ext-openswoole/contributors",
  "subscribers_url": "https://api.github.com/repos/openswoole/ext-openswoole/subscribers",
  "subscription_url": "https://api.github.com/repos/openswoole/ext-openswoole/subscription",
  "commits_url": "https://api.github.com/repos/openswoole/ext-openswoole/commits{/sha}",
  "git_commits_url": "https://api.github.com/repos/openswoole/ext-openswoole/git/commits{/sha}",
  "comments_url": "https://api.github.com/repos/openswoole/ext-openswoole/comments{/number}",
  "issue_comment_url": "https://api.github.com/repos/openswoole/ext-openswoole/issues/comments{/number}",
  "contents_url": "https://api.github.com/repos/openswoole/ext-openswoole/contents/{+path}",
  "compare_url": "https://api.github.com/repos/openswoole/ext-openswoole/compare/{base}...{head}",
  "merges_url": "https://api.github.com/repos/openswoole/ext-openswoole/merges",
  "archive_url": "https://api.github.com/repos/openswoole/ext-openswoole/{archive_format}{/ref}",
  "downloads_url": "https://api.github.com/repos/openswoole/ext-openswoole/downloads",
  "issues_url": "https://api.github.com/repos/openswoole/ext-openswoole/issues{/number}",
  "pulls_url": "https://api.github.com/repos/openswoole/ext-openswoole/pulls{/number}",
  "milestones_url": "https://api.github.com/repos/openswoole/ext-openswoole/milestones{/number}",
  "notifications_url": "https://api.github.com/repos/openswoole/ext-openswoole/notifications{?since,all,participating}",
  "labels_url": "https://api.github.com/repos/openswoole/ext-openswoole/labels{/name}",
  "releases_url": "https://api.github.com/repos/openswoole/ext-openswoole/releases{/id}",
  "deployments_url": "https://api.github.com/repos/openswoole/ext-openswoole/deployments",
  "created_at": "2021-10-13T08:44:11Z",
  "updated_at": "2025-08-02T13:43:48Z",
  "pushed_at": "2025-02-04T09:43:33Z",
  "git_url": "git://github.com/openswoole/ext-openswoole.git",
  "ssh_url": "git@github.com:openswoole/ext-openswoole.git",
  "clone_url": "https://github.com/openswoole/ext-openswoole.git",
  "svn_url": "https://github.com/openswoole/ext-openswoole",
  "homepage": "https://openswoole.com",
  "size": 47512,
  "stargazers_count": 828,
  "watchers_count": 828,
  "language": "C++",
  "has_issues": true,
  "has_projects": true,
  "has_downloads": true,
  "has_wiki": true,
  "has_pages": false,
  "has_discussions": false,
  "forks_count": 54,
  "mirror_url": null,
  "archived": false,
  "disabled": false,
  "open_issues_count": 43,
  "license": {
    "key": "apache-2.0",
    "name": "Apache License 2.0",
    "spdx_id": "Apache-2.0",
    "url": "https://api.github.com/licenses/apache-2.0",
    "node_id": "MDc6TGljZW5zZTI="
  },
  "allow_forking": true,
  "is_template": false,
  "web_commit_signoff_required": false,
  "topics": [
    "async",
    "concurrency",
    "coroutines",
    "openswoole",
    "php"
  ],
  "visibility": "public",
  "forks": 54,
  "open_issues": 43,
  "watchers": 828,
  "default_branch": "master",
  "permissions": {
    "admin": false,
    "maintain": false,
    "push": false,
    "triage": false,
    "pull": true
  },
  "score": 1.0
}