{
  "id": 402337547,
  "node_id": "MDEwOlJlcG9zaXRvcnk0MDIzMzc1NDc=",
  "name": "BusinessCentral.LinterCop",
  "full_name": "StefanMaron/BusinessCentral.LinterCop",
  "private": false,
  "owner": {
    "login": "StefanMaron",
    "id": 24838311,
    "node_id": "MDQ6VXNlcjI0ODM4MzEx",
    "avatar_url": "https://avatars.githubusercontent.com/u/24838311?v=4",
    "gravatar_id": "",
    "url": "https://api.github.com/users/StefanMaron",
    "html_url": "https://github.com/StefanMaron",
    "followers_url": "https://api.github.com/users/StefanMaron/followers",
    "following_url": "https://api.github.com/users/StefanMaron/following{/other_user}",
    "gists_url": "https://api.github.com/users/StefanMaron/gists{/gist_id}",
    "starred_url": "https://api.github.com/users/StefanMaron/starred{/owner}{/repo}",
    "subscriptions_url": "https://api.github.com/users/StefanMaron/subscriptions",
    "organizations_url": "https://api.github.com/users/StefanMaron/orgs",
    "repos_url": "https://api.github.com/users/StefanMaron/repos",
    "events_url": "https://api.github.com/users/StefanMaron/events{/privacy}",
    "received_events_url": "https://api.github.com/users/StefanMaron/received_events",
    "type": "User",
    "user_view_type": "public",
    "site_admin": false
  },
  "html_url": "https://github.com/StefanMaron/BusinessCentral.LinterCop",
  "description": "Community driven code linter for AL (MS Dynamics 365 Business Central) ",
  "fork": false,
  "url": "https://api.github.com/repos/StefanMaron/BusinessCentral.LinterCop",
  "forks_url": "https://api.github.com/repos/StefanMaron/BusinessCentral.LinterCop/forks",
  "keys_url": "https://api.github.com/repos/StefanMaron/BusinessCentral.LinterCop/keys{/key_id}",
  "collaborators_url": "https://api.github.com/repos/StefanMaron/BusinessCentral.LinterCop/collaborators{/collaborator}",
  "teams_url": "https://api.github.com/repos/StefanMaron/BusinessCentral.LinterCop/teams",
  "hooks_url": "https://api.github.com/repos/StefanMaron/BusinessCentral.LinterCop/hooks",
  "issue_events_url": "https://api.github.com/repos/StefanMaron/BusinessCentral.LinterCop/issues/events{/number}",
  "events_url": "https://api.github.com/repos/StefanMaron/BusinessCentral.LinterCop/events",
  "assignees_url": "https://api.github.com/repos/StefanMaron/BusinessCentral.LinterCop/assignees{/user}",
  "branches_url": "https://api.github.com/repos/StefanMaron/BusinessCentral.LinterCop/branches{/branch}",
  "tags_url": "https://api.github.com/repos/StefanMaron/BusinessCentral.LinterCop/tags",
  "blobs_url": "https://api.github.com/repos/StefanMaron/BusinessCentral.LinterCop/git/blobs{/sha}",
  "git_tags_url": "https://api.github.com/repos/StefanMaron/BusinessCentral.LinterCop/git/tags{/sha}",
  "git_refs_url": "https://api.github.com/repos/StefanMaron/BusinessCentral.LinterCop/git/refs{/sha}",
  "trees_url": "https://api.github.com/repos/StefanMaron/BusinessCentral.LinterCop/git/trees{/sha}",
  "statuses_url": "https://api.github.com/repos/StefanMaron/BusinessCentral.LinterCop/statuses/{sha}",
  "languages_url": "https://api.github.com/repos/StefanMaron/BusinessCentral.LinterCop/languages",
  "stargazers_url": "https://api.github.com/repos/StefanMaron/BusinessCentral.LinterCop/stargazers",
  "contributors_url": "https://api.github.com/repos/StefanMaron/BusinessCentral.LinterCop/contributors",
  "subscribers_url": "https://api.github.com/repos/StefanMaron/BusinessCentral.LinterCop/subscribers",
  "subscription_url": "https://api.github.com/repos/StefanMaron/BusinessCentral.LinterCop/subscription",
  "commits_url": "https://api.github.com/repos/StefanMaron/BusinessCentral.LinterCop/commits{/sha}",
  "git_commits_url": "https://api.github.com/repos/StefanMaron/BusinessCentral.LinterCop/git/commits{/sha}",
  "comments_url": "https://api.github.com/repos/StefanMaron/BusinessCentral.LinterCop/comments{/number}",
  "issue_comment_url": "https://api.github.com/repos/StefanMaron/BusinessCentral.LinterCop/issues/comments{/number}",
  "contents_url": "https://api.github.com/repos/StefanMaron/BusinessCentral.LinterCop/contents/{+path}",
  "compare_url": "https://api.github.com/repos/StefanMaron/BusinessCentral.LinterCop/compare/{base}...{head}",
  "merges_url": "https://api.github.com/repos/StefanMaron/BusinessCentral.LinterCop/merges",
  "archive_url": "https://api.github.com/repos/StefanMaron/BusinessCentral.LinterCop/{archive_format}{/ref}",
  "downloads_url": "https://api.github.com/repos/StefanMaron/BusinessCentral.LinterCop/downloads",
  "issues_url": "https://api.github.com/repos/StefanMaron/BusinessCentral.LinterCop/issues{/number}",
  "pulls_url": "https://api.github.com/repos/StefanMaron/BusinessCentral.LinterCop/pulls{/number}",
  "milestones_url": "https://api.github.com/repos/StefanMaron/BusinessCentral.LinterCop/milestones{/number}",
  "notifications_url": "https://api.github.com/repos/StefanMaron/BusinessCentral.LinterCop/notifications{?since,all,participating}",
  "labels_url": "https://api.github.com/repos/StefanMaron/BusinessCentral.LinterCop/labels{/name}",
  "releases_url": "https://api.github.com/repos/StefanMaron/BusinessCentral.LinterCop/releases{/id}",
  "deployments_url": "https://api.github.com/repos/StefanMaron/BusinessCentral.LinterCop/deployments",
  "created_at": "2021-09-02T07:57:09Z",
  "updated_at": "2025-07-25T20:09:18Z",
  "pushed_at": "2025-08-01T16:01:07Z",
  "git_url": "git://github.com/StefanMaron/BusinessCentral.LinterCop.git",
  "ssh_url": "git@github.com:StefanMaron/BusinessCentral.LinterCop.git",
  "clone_url": "https://github.com/StefanMaron/BusinessCentral.LinterCop.git",
  "svn_url": "https://github.com/StefanMaron/BusinessCentral.LinterCop",
  "homepage": "https://stefanmaron.com",
  "size": 1447,
  "stargazers_count": 97,
  "watchers_count": 97,
  "language": "C#",
  "has_issues": true,
  "has_projects": false,
  "has_downloads": true,
  "has_wiki": true,
  "has_pages": false,
  "has_discussions": true,
  "forks_count": 37,
  "mirror_url": null,
  "archived": false,
  "disabled": false,
  "open_issues_count": 55,
  "license": {
    "key": "mit",
    "name": "MIT License",
    "spdx_id": "MIT",
    "url": "https://api.github.com/licenses/mit",
    "node_id": "MDc6TGljZW5zZTEz"
  },
  "allow_forking": true,
  "is_template": false,
  "web_commit_signoff_required": false,
  "topics": [
    "al",
    "businesscentral",
    "clean-code",
    "linter",
    "msdyn365bc"
  ],
  "visibility": "public",
  "forks": 37,
  "open_issues": 55,
  "watchers": 97,
  "default_branch": "master",
  "permissions": {
    "admin": false,
    "maintain": false,
    "push": false,
    "triage": false,
    "pull": true
  },
  "score": 1.0
}