{
  "id": 483176101,
  "node_id": "R_kgDOHMyupQ",
  "name": "Velvet",
  "full_name": "vitalight/Velvet",
  "private": false,
  "owner": {
    "login": "vitalight",
    "id": 28224377,
    "node_id": "MDQ6VXNlcjI4MjI0Mzc3",
    "avatar_url": "https://avatars.githubusercontent.com/u/28224377?v=4",
    "gravatar_id": "",
    "url": "https://api.github.com/users/vitalight",
    "html_url": "https://github.com/vitalight",
    "followers_url": "https://api.github.com/users/vitalight/followers",
    "following_url": "https://api.github.com/users/vitalight/following{/other_user}",
    "gists_url": "https://api.github.com/users/vitalight/gists{/gist_id}",
    "starred_url": "https://api.github.com/users/vitalight/starred{/owner}{/repo}",
    "subscriptions_url": "https://api.github.com/users/vitalight/subscriptions",
    "organizations_url": "https://api.github.com/users/vitalight/orgs",
    "repos_url": "https://api.github.com/users/vitalight/repos",
    "events_url": "https://api.github.com/users/vitalight/events{/privacy}",
    "received_events_url": "https://api.github.com/users/vitalight/received_events",
    "type": "User",
    "user_view_type": "public",
    "site_admin": false
  },
  "html_url": "https://github.com/vitalight/Velvet",
  "description": "A CUDA-accelerated cloth simulation engine based on Extended Position Based Dynamics (XPBD).",
  "fork": false,
  "url": "https://api.github.com/repos/vitalight/Velvet",
  "forks_url": "https://api.github.com/repos/vitalight/Velvet/forks",
  "keys_url": "https://api.github.com/repos/vitalight/Velvet/keys{/key_id}",
  "collaborators_url": "https://api.github.com/repos/vitalight/Velvet/collaborators{/collaborator}",
  "teams_url": "https://api.github.com/repos/vitalight/Velvet/teams",
  "hooks_url": "https://api.github.com/repos/vitalight/Velvet/hooks",
  "issue_events_url": "https://api.github.com/repos/vitalight/Velvet/issues/events{/number}",
  "events_url": "https://api.github.com/repos/vitalight/Velvet/events",
  "assignees_url": "https://api.github.com/repos/vitalight/Velvet/assignees{/user}",
  "branches_url": "https://api.github.com/repos/vitalight/Velvet/branches{/branch}",
  "tags_url": "https://api.github.com/repos/vitalight/Velvet/tags",
  "blobs_url": "https://api.github.com/repos/vitalight/Velvet/git/blobs{/sha}",
  "git_tags_url": "https://api.github.com/repos/vitalight/Velvet/git/tags{/sha}",
  "git_refs_url": "https://api.github.com/repos/vitalight/Velvet/git/refs{/sha}",
  "trees_url": "https://api.github.com/repos/vitalight/Velvet/git/trees{/sha}",
  "statuses_url": "https://api.github.com/repos/vitalight/Velvet/statuses/{sha}",
  "languages_url": "https://api.github.com/repos/vitalight/Velvet/languages",
  "stargazers_url": "https://api.github.com/repos/vitalight/Velvet/stargazers",
  "contributors_url": "https://api.github.com/repos/vitalight/Velvet/contributors",
  "subscribers_url": "https://api.github.com/repos/vitalight/Velvet/subscribers",
  "subscription_url": "https://api.github.com/repos/vitalight/Velvet/subscription",
  "commits_url": "https://api.github.com/repos/vitalight/Velvet/commits{/sha}",
  "git_commits_url": "https://api.github.com/repos/vitalight/Velvet/git/commits{/sha}",
  "comments_url": "https://api.github.com/repos/vitalight/Velvet/comments{/number}",
  "issue_comment_url": "https://api.github.com/repos/vitalight/Velvet/issues/comments{/number}",
  "contents_url": "https://api.github.com/repos/vitalight/Velvet/contents/{+path}",
  "compare_url": "https://api.github.com/repos/vitalight/Velvet/compare/{base}...{head}",
  "merges_url": "https://api.github.com/repos/vitalight/Velvet/merges",
  "archive_url": "https://api.github.com/repos/vitalight/Velvet/{archive_format}{/ref}",
  "downloads_url": "https://api.github.com/repos/vitalight/Velvet/downloads",
  "issues_url": "https://api.github.com/repos/vitalight/Velvet/issues{/number}",
  "pulls_url": "https://api.github.com/repos/vitalight/Velvet/pulls{/number}",
  "milestones_url": "https://api.github.com/repos/vitalight/Velvet/milestones{/number}",
  "notifications_url": "https://api.github.com/repos/vitalight/Velvet/notifications{?since,all,participating}",
  "labels_url": "https://api.github.com/repos/vitalight/Velvet/labels{/name}",
  "releases_url": "https://api.github.com/repos/vitalight/Velvet/releases{/id}",
  "deployments_url": "https://api.github.com/repos/vitalight/Velvet/deployments",
  "created_at": "2022-04-19T09:16:30Z",
  "updated_at": "2025-06-24T11:20:14Z",
  "pushed_at": "2025-03-20T13:53:45Z",
  "git_url": "git://github.com/vitalight/Velvet.git",
  "ssh_url": "git@github.com:vitalight/Velvet.git",
  "clone_url": "https://github.com/vitalight/Velvet.git",
  "svn_url": "https://github.com/vitalight/Velvet",
  "homepage": "",
  "size": 58255,
  "stargazers_count": 185,
  "watchers_count": 185,
  "language": "C++",
  "has_issues": true,
  "has_projects": false,
  "has_downloads": true,
  "has_wiki": false,
  "has_pages": false,
  "has_discussions": false,
  "forks_count": 30,
  "mirror_url": null,
  "archived": false,
  "disabled": false,
  "open_issues_count": 3,
  "license": {
    "key": "mit",
    "name": "MIT License",
    "spdx_id": "MIT",
    "url": "https://api.github.com/licenses/mit",
    "node_id": "MDc6TGljZW5zZTEz"
  },
  "allow_forking": true,
  "is_template": false,
  "web_commit_signoff_required": false,
  "topics": [
    "c-plus-plus",
    "cloth-simulation",
    "computer-graphics",
    "cuda",
    "gpu",
    "physics-simulation",
    "position-based-dynamics"
  ],
  "visibility": "public",
  "forks": 30,
  "open_issues": 3,
  "watchers": 185,
  "default_branch": "master",
  "permissions": {
    "admin": false,
    "maintain": false,
    "push": false,
    "triage": false,
    "pull": true
  },
  "score": 1.0
}