{
  "id": 116631863,
  "node_id": "MDEwOlJlcG9zaXRvcnkxMTY2MzE4NjM=",
  "name": ".homeassistant",
  "full_name": "Yonsm/.homeassistant",
  "private": false,
  "owner": {
    "login": "Yonsm",
    "id": 1648076,
    "node_id": "MDQ6VXNlcjE2NDgwNzY=",
    "avatar_url": "https://avatars.githubusercontent.com/u/1648076?v=4",
    "gravatar_id": "",
    "url": "https://api.github.com/users/Yonsm",
    "html_url": "https://github.com/Yonsm",
    "followers_url": "https://api.github.com/users/Yonsm/followers",
    "following_url": "https://api.github.com/users/Yonsm/following{/other_user}",
    "gists_url": "https://api.github.com/users/Yonsm/gists{/gist_id}",
    "starred_url": "https://api.github.com/users/Yonsm/starred{/owner}{/repo}",
    "subscriptions_url": "https://api.github.com/users/Yonsm/subscriptions",
    "organizations_url": "https://api.github.com/users/Yonsm/orgs",
    "repos_url": "https://api.github.com/users/Yonsm/repos",
    "events_url": "https://api.github.com/users/Yonsm/events{/privacy}",
    "received_events_url": "https://api.github.com/users/Yonsm/received_events",
    "type": "User",
    "user_view_type": "public",
    "site_admin": false
  },
  "html_url": "https://github.com/Yonsm/.homeassistant",
  "description": "Home Assistant Extras for Yonsm",
  "fork": false,
  "url": "https://api.github.com/repos/Yonsm/.homeassistant",
  "forks_url": "https://api.github.com/repos/Yonsm/.homeassistant/forks",
  "keys_url": "https://api.github.com/repos/Yonsm/.homeassistant/keys{/key_id}",
  "collaborators_url": "https://api.github.com/repos/Yonsm/.homeassistant/collaborators{/collaborator}",
  "teams_url": "https://api.github.com/repos/Yonsm/.homeassistant/teams",
  "hooks_url": "https://api.github.com/repos/Yonsm/.homeassistant/hooks",
  "issue_events_url": "https://api.github.com/repos/Yonsm/.homeassistant/issues/events{/number}",
  "events_url": "https://api.github.com/repos/Yonsm/.homeassistant/events",
  "assignees_url": "https://api.github.com/repos/Yonsm/.homeassistant/assignees{/user}",
  "branches_url": "https://api.github.com/repos/Yonsm/.homeassistant/branches{/branch}",
  "tags_url": "https://api.github.com/repos/Yonsm/.homeassistant/tags",
  "blobs_url": "https://api.github.com/repos/Yonsm/.homeassistant/git/blobs{/sha}",
  "git_tags_url": "https://api.github.com/repos/Yonsm/.homeassistant/git/tags{/sha}",
  "git_refs_url": "https://api.github.com/repos/Yonsm/.homeassistant/git/refs{/sha}",
  "trees_url": "https://api.github.com/repos/Yonsm/.homeassistant/git/trees{/sha}",
  "statuses_url": "https://api.github.com/repos/Yonsm/.homeassistant/statuses/{sha}",
  "languages_url": "https://api.github.com/repos/Yonsm/.homeassistant/languages",
  "stargazers_url": "https://api.github.com/repos/Yonsm/.homeassistant/stargazers",
  "contributors_url": "https://api.github.com/repos/Yonsm/.homeassistant/contributors",
  "subscribers_url": "https://api.github.com/repos/Yonsm/.homeassistant/subscribers",
  "subscription_url": "https://api.github.com/repos/Yonsm/.homeassistant/subscription",
  "commits_url": "https://api.github.com/repos/Yonsm/.homeassistant/commits{/sha}",
  "git_commits_url": "https://api.github.com/repos/Yonsm/.homeassistant/git/commits{/sha}",
  "comments_url": "https://api.github.com/repos/Yonsm/.homeassistant/comments{/number}",
  "issue_comment_url": "https://api.github.com/repos/Yonsm/.homeassistant/issues/comments{/number}",
  "contents_url": "https://api.github.com/repos/Yonsm/.homeassistant/contents/{+path}",
  "compare_url": "https://api.github.com/repos/Yonsm/.homeassistant/compare/{base}...{head}",
  "merges_url": "https://api.github.com/repos/Yonsm/.homeassistant/merges",
  "archive_url": "https://api.github.com/repos/Yonsm/.homeassistant/{archive_format}{/ref}",
  "downloads_url": "https://api.github.com/repos/Yonsm/.homeassistant/downloads",
  "issues_url": "https://api.github.com/repos/Yonsm/.homeassistant/issues{/number}",
  "pulls_url": "https://api.github.com/repos/Yonsm/.homeassistant/pulls{/number}",
  "milestones_url": "https://api.github.com/repos/Yonsm/.homeassistant/milestones{/number}",
  "notifications_url": "https://api.github.com/repos/Yonsm/.homeassistant/notifications{?since,all,participating}",
  "labels_url": "https://api.github.com/repos/Yonsm/.homeassistant/labels{/name}",
  "releases_url": "https://api.github.com/repos/Yonsm/.homeassistant/releases{/id}",
  "deployments_url": "https://api.github.com/repos/Yonsm/.homeassistant/deployments",
  "created_at": "2018-01-08T05:00:07Z",
  "updated_at": "2025-07-29T07:16:54Z",
  "pushed_at": "2025-02-23T16:59:32Z",
  "git_url": "git://github.com/Yonsm/.homeassistant.git",
  "ssh_url": "git@github.com:Yonsm/.homeassistant.git",
  "clone_url": "https://github.com/Yonsm/.homeassistant.git",
  "svn_url": "https://github.com/Yonsm/.homeassistant",
  "homepage": "",
  "size": 26204,
  "stargazers_count": 421,
  "watchers_count": 421,
  "language": "Python",
  "has_issues": true,
  "has_projects": true,
  "has_downloads": true,
  "has_wiki": true,
  "has_pages": false,
  "has_discussions": false,
  "forks_count": 139,
  "mirror_url": null,
  "archived": false,
  "disabled": false,
  "open_issues_count": 19,
  "license": null,
  "allow_forking": true,
  "is_template": false,
  "web_commit_signoff_required": false,
  "topics": [],
  "visibility": "public",
  "forks": 139,
  "open_issues": 19,
  "watchers": 421,
  "default_branch": "main",
  "permissions": {
    "admin": false,
    "maintain": false,
    "push": false,
    "triage": false,
    "pull": true
  },
  "score": 1.0
}